{"code":"5610","name":"ristoranti e attività di ristorazione mobile","count":15,"companies":[{"id":"IT-00012","name":"Trattoria del Borgo Srl","ateco":"5610","ateco_label":"ristoranti e attività di ristorazione mobile","comune":"Bologna","provincia":"BO","regione":"Emilia-Romagna","forma_giuridica":"SRL","stato":"attiva","pec":"trattoriaborgo@pec.it","website":null,"anno":2023,"fields":{"fatturato":{"value":1250,"state":"osservato","unit":"keur"},"addetti":{"value":22,"state":"osservato","unit":"n"},"valore_aggiunto":{"value":540,"state":"osservato","unit":"keur"},"mol":{"value":110,"state":"osservato","unit":"keur"},"margine":{"value":0.088,"state":"osservato","unit":"ratio"},"produttivita":{"value":24.55,"state":"osservato","unit":"keur"}}},{"id":"IT-00013","name":"Osteria Marina Srl","ateco":"5610","ateco_label":"ristoranti e attività di ristorazione mobile","comune":"Genova","provincia":"GE","regione":"Liguria","forma_giuridica":"SRL","stato":"attiva","pec":"osteriamarina@pec.it","website":null,"anno":2023,"fields":{"fatturato":{"value":980,"state":"osservato","unit":"keur"},"addetti":{"value":16,"state":"osservato","unit":"n"},"valore_aggiunto":{"value":410,"state":"osservato","unit":"keur"},"mol":{"value":72,"state":"osservato","unit":"keur"},"margine":{"value":0.0735,"state":"osservato","unit":"ratio"},"produttivita":{"value":25.62,"state":"osservato","unit":"keur"}}},{"id":"IT-00014","name":"Ristorante Aurora SpA","ateco":"5610","ateco_label":"ristoranti e attività di ristorazione mobile","comune":"Milano","provincia":"MI","regione":"Lombardia","forma_giuridica":"SPA","stato":"attiva","pec":"ristoranteaurora@pec.it","website":"ristoranteaurora.example.it","anno":2023,"fields":{"fatturato":{"value":5600,"state":"osservato","unit":"keur"},"addetti":{"value":74,"state":"osservato","unit":"n"},"valore_aggiunto":{"value":2300,"state":"osservato","unit":"keur"},"mol":{"value":480,"state":"osservato","unit":"keur"},"margine":{"value":0.0857,"state":"osservato","unit":"ratio"},"produttivita":{"value":31.08,"state":"osservato","unit":"keur"}}},{"id":"IT-00015","name":"Pizzeria Napoli Verace Srl","ateco":"5610","ateco_label":"ristoranti e attività di ristorazione mobile","comune":"Napoli","provincia":"NA","regione":"Campania","forma_giuridica":"SRL","stato":"attiva","pec":"pizzerianapoli@pec.it","website":null,"anno":2023,"fields":{"fatturato":{"value":720,"state":"osservato","unit":"keur"},"addetti":{"value":14,"state":"osservato","unit":"n"},"valore_aggiunto":{"value":300,"state":"osservato","unit":"keur"},"mol":{"value":58,"state":"osservato","unit":"keur"},"margine":{"value":0.0806,"state":"osservato","unit":"ratio"},"produttivita":{"value":21.43,"state":"osservato","unit":"keur"}}},{"id":"IT-00016","name":"La Tavola Toscana Srl","ateco":"5610","ateco_label":"ristoranti e attività di ristorazione mobile","comune":"Firenze","provincia":"FI","regione":"Toscana","forma_giuridica":"SRL","stato":"attiva","pec":"tavolatoscana@pec.it","website":null,"anno":2023,"fields":{"fatturato":{"value":1420,"state":"osservato","unit":"keur"},"addetti":{"value":24,"state":"osservato","unit":"n"},"valore_aggiunto":{"value":610,"state":"osservato","unit":"keur"},"mol":{"value":120,"state":"osservato","unit":"keur"},"margine":{"value":0.0845,"state":"osservato","unit":"ratio"},"produttivita":{"value":25.42,"state":"osservato","unit":"keur"}}},{"id":"IT-00017","name":"Sapori di Sicilia Srl","ateco":"5610","ateco_label":"ristoranti e attività di ristorazione mobile","comune":"Palermo","provincia":"PA","regione":"Sicilia","forma_giuridica":"SRL","stato":"attiva","pec":"saporisicilia@pec.it","website":null,"anno":2023,"fields":{"fatturato":{"value":860,"state":"osservato","unit":"keur"},"addetti":{"value":15,"state":"osservato","unit":"n"},"valore_aggiunto":{"value":360,"state":"osservato","unit":"keur"},"mol":{"value":66,"state":"osservato","unit":"keur"},"margine":{"value":0.0767,"state":"osservato","unit":"ratio"},"produttivita":{"value":24.0,"state":"osservato","unit":"keur"}}},{"id":"IT-00018","name":"Braceria Centrale Srl","ateco":"5610","ateco_label":"ristoranti e attività di ristorazione mobile","comune":"Roma","provincia":"RM","regione":"Lazio","forma_giuridica":"SRL","stato":"attiva","pec":"braceriacentrale@pec.it","website":null,"anno":2023,"fields":{"fatturato":{"value":2100,"state":"osservato","unit":"keur"},"addetti":{"value":31,"state":"osservato","unit":"n"},"valore_aggiunto":{"value":880,"state":"osservato","unit":"keur"},"mol":{"value":175,"state":"osservato","unit":"keur"},"margine":{"value":0.0833,"state":"osservato","unit":"ratio"},"produttivita":{"value":28.39,"state":"osservato","unit":"keur"}}},{"id":"IT-00019","name":"Bistrot Lago Srl","ateco":"5610","ateco_label":"ristoranti e attività di ristorazione mobile","comune":"Como","provincia":"CO","regione":"Lombardia","forma_giuridica":"SRL","stato":"attiva","pec":"bistrotlago@pec.it","website":null,"anno":2023,"fields":{"fatturato":{"value":1100,"state":"osservato","unit":"keur"},"addetti":{"value":18,"state":"osservato","unit":"n"},"valore_aggiunto":{"value":470,"state":"osservato","unit":"keur"},"mol":{"value":95,"state":"osservato","unit":"keur"},"margine":{"value":0.0864,"state":"osservato","unit":"ratio"},"produttivita":{"value":26.11,"state":"osservato","unit":"keur"}}},{"id":"IT-00020","name":"Cucina Adriatica Srl","ateco":"5610","ateco_label":"ristoranti e attività di ristorazione mobile","comune":"Pescara","provincia":"PE","regione":"Abruzzo","forma_giuridica":"SRL","stato":"attiva","pec":"cucinaadriatica@pec.it","website":null,"anno":2023,"fields":{"fatturato":{"value":640,"state":"osservato","unit":"keur"},"addetti":{"value":12,"state":"osservato","unit":"n"},"valore_aggiunto":{"value":270,"state":"osservato","unit":"keur"},"mol":{"value":50,"state":"osservato","unit":"keur"},"margine":{"value":0.0781,"state":"osservato","unit":"ratio"},"produttivita":{"value":22.5,"state":"osservato","unit":"keur"}}},{"id":"IT-00021","name":"Ristoro Alpino Srl","ateco":"5610","ateco_label":"ristoranti e attività di ristorazione mobile","comune":"Bolzano","provincia":"BZ","regione":"Trentino-Alto Adige","forma_giuridica":"SRL","stato":"attiva","pec":"ristoroalpino@pec.it","website":null,"anno":2023,"fields":{"fatturato":{"value":1330,"state":"osservato","unit":"keur"},"addetti":{"value":21,"state":"osservato","unit":"n"},"valore_aggiunto":{"value":560,"state":"osservato","unit":"keur"},"mol":{"value":112,"state":"osservato","unit":"keur"},"margine":{"value":0.0842,"state":"osservato","unit":"ratio"},"produttivita":{"value":26.67,"state":"osservato","unit":"keur"}}},{"id":"IT-00022","name":"Piazza Grande Ristoranti SpA","ateco":"5610","ateco_label":"ristoranti e attività di ristorazione mobile","comune":"Torino","provincia":"TO","regione":"Piemonte","forma_giuridica":"SPA","stato":"attiva","pec":"piazzagrande@pec.it","website":"piazzagrande.example.it","anno":2023,"fields":{"fatturato":{"value":7800,"state":"osservato","unit":"keur"},"addetti":{"value":96,"state":"osservato","unit":"n"},"valore_aggiunto":{"value":3200,"state":"osservato","unit":"keur"},"mol":{"value":690,"state":"osservato","unit":"keur"},"margine":{"value":0.0885,"state":"osservato","unit":"ratio"},"produttivita":{"value":33.33,"state":"osservato","unit":"keur"}}},{"id":"IT-00023","name":"Locanda del Sole Srl","ateco":"5610","ateco_label":"ristoranti e attività di ristorazione mobile","comune":"Lecce","provincia":"LE","regione":"Puglia","forma_giuridica":"SRL","stato":"attiva","pec":"locandasole@pec.it","website":null,"anno":2023,"fields":{"fatturato":{"value":590,"state":"osservato","unit":"keur"},"addetti":{"value":11,"state":"osservato","unit":"n"},"valore_aggiunto":{"value":250,"state":"osservato","unit":"keur"},"mol":{"value":46,"state":"osservato","unit":"keur"},"margine":{"value":0.078,"state":"osservato","unit":"ratio"},"produttivita":{"value":22.73,"state":"osservato","unit":"keur"}}},{"id":"IT-00024","name":"Trattoria Vecchia Srl","ateco":"5610","ateco_label":"ristoranti e attività di ristorazione mobile","comune":"Verona","provincia":"VR","regione":"Veneto","forma_giuridica":"SRL","stato":"attiva","pec":"trattoriavecchia@pec.it","website":null,"anno":2023,"fields":{"fatturato":{"value":1010,"state":"osservato","unit":"keur"},"addetti":{"value":17,"state":"osservato","unit":"n"},"valore_aggiunto":{"value":430,"state":"osservato","unit":"keur"},"mol":{"value":86,"state":"osservato","unit":"keur"},"margine":{"value":0.0851,"state":"osservato","unit":"ratio"},"produttivita":{"value":25.29,"state":"osservato","unit":"keur"}}},{"id":"IT-00025","name":"Gusto Urbano Srl","ateco":"5610","ateco_label":"ristoranti e attività di ristorazione mobile","comune":"Milano","provincia":"MI","regione":"Lombardia","forma_giuridica":"SRL","stato":"attiva","pec":"gustourbano@pec.it","website":"gustourbano.example.it","anno":2023,"fields":{"fatturato":{"value":3400,"state":"osservato","unit":"keur"},"addetti":{"value":44,"state":"osservato","unit":"n"},"valore_aggiunto":{"value":1400,"state":"osservato","unit":"keur"},"mol":{"value":290,"state":"osservato","unit":"keur"},"margine":{"value":0.0853,"state":"osservato","unit":"ratio"},"produttivita":{"value":31.82,"state":"osservato","unit":"keur"}}},{"id":"IT-00026","name":"Cascina Ristoro Srl","ateco":"5610","ateco_label":"ristoranti e attività di ristorazione mobile","comune":"Cuneo","provincia":"CN","regione":"Piemonte","forma_giuridica":"SRL","stato":"cessata","pec":"cascinaristoro@pec.it","website":null,"anno":2022,"fields":{"fatturato":{"value":410,"state":"osservato","unit":"keur"},"addetti":{"value":8,"state":"osservato","unit":"n"},"valore_aggiunto":{"value":170,"state":"osservato","unit":"keur"},"mol":{"value":28,"state":"osservato","unit":"keur"},"margine":{"value":0.0683,"state":"osservato","unit":"ratio"},"produttivita":{"value":21.25,"state":"osservato","unit":"keur"}}}]}